devices/__init__.py
devices/dm_camera.py
devices/dm_microscope.py
devices/dm_pyjem_microscope.py
devices/dm_pyjem_test_microscope.py
devices/dm_test_camera.py
devices/dm_test_microscope.py
devices/dummy_camera.py
devices/dummy_microscope.py
devices/pyjem_camera.py
devices/pyjem_microscope.py
devices/pyjem_olcurrent.py
devices/pyjem_test_microscope.py
pylo/__init__.py
pylo/__main__.py
pylo/abstract_configuration.py
pylo/abstract_view.py
pylo/blocked_function.py
pylo/camera_interface.py
pylo/cli_view.py
pylo/config.py
pylo/controller.py
pylo/datatype.py
pylo/default_datatypes.py
pylo/device.py
pylo/device_loader.py
pylo/dm_configuration.py
pylo/dm_image.py
pylo/dm_view.py
pylo/errors.py
pylo/event.py
pylo/events.py
pylo/exception_thread.py
pylo/image.py
pylo/ini_configuration.py
pylo/log_thread.py
pylo/logginglib.py
pylo/measurement.py
pylo/measurement_steps.py
pylo/measurement_variable.py
pylo/microscope_interface.py
pylo/pylodmlib.py
pylo/pylolib.py
pylo/stop_program.py
pylo/vulnerable_machine.py
PyLo-1.0.0.dist-info/LICENSE
PyLo-1.0.0.dist-info/METADATA
PyLo-1.0.0.dist-info/WHEEL
PyLo-1.0.0.dist-info/top_level.txt
PyLo-1.0.0.dist-info/RECORD
