Metadata-Version: 2.1
Name: PyLo
Version: 1.0.0
Summary: A python program to record image series with Lorentz-TEM.
Home-page: https://github.com/miile7/pylo-project
Author: miile7
Author-email: miile7@gmx.de
License: UNKNOWN
Platform: UNKNOWN
Classifier: Programming Language :: Python :: 3
Classifier: Intended Audience :: Science/Research
Classifier: Topic :: Scientific/Engineering :: Physics
Requires-Python: >=3.5
